RAM/DualPortRAM/DualPortRAM.v
module DualPortRAM(
    input clk,
    input write1,
    input read1,
    input [9:0] addr1,
    input [7:0] data_in1,
    input write2,
    input read2,
    input [9:0] addr2,
    input [7:0] data_in2,
    input cs,
    output reg [7:0] data_out1,
    output reg [7:0] data_out2
);
    reg [7:0] Memory[0:1023];
    always @(posedge clk) begin
        if(cs)begin
            if(write1)
                Memory[addr1]<=data_in1;
            else if(read1)
                data_out1<=Memory[addr1];
        end
    end
    always @(posedge clk) begin
        if(cs)begin
            if(write2)
                Memory[addr2]<=data_in2;
            else if(read2)
                data_out2<=Memory[addr2];
        end
    end

endmodule

RAM/DualPortRAM/tb_DualPortRAM.v
module tb_DualPortRAM;
    reg clk,write1,read1,write2,read2,cs;
    reg [7:0] data_in1,data_in2;
    reg [9:0] addr1,addr2;
    wire [7:0] data_out1,data_out2;
    integer k;

    DualPortRAM DUT(clk,write1,read1,addr1,data_in1,write2,read2,
    addr2,data_in2,cs,data_out1,data_out2);

    initial begin
        clk=0;
        cs=1;
    end
    always #5 clk=~clk;
    initial begin
        for(k=0;k<10;k=k+1) 
            DUT.Memory[k]= #10 k*10;
        #10 read1=1;addr1=10'h000;read2=1;addr2=10'h001;
        
        #10 $finish;
    end
    initial begin
        $dumpfile("DualPortRAM.vcd");
        $dumpvars(0,tb_DualPortRAM);
    end

endmodule

RAM/DualPortRAM/DualPortRAM.vcd
$date
	Tue Jul 28 16:09:07 2026
$end
$version
	Icarus Verilog
$end
$timescale
	1s
$end
$scope module tb_DualPortRAM $end
$var wire 8 ! data_out2 [7:0] $end
$var wire 8 " data_out1 [7:0] $end
$var reg 10 # addr1 [9:0] $end
$var reg 10 $ addr2 [9:0] $end
$var reg 1 % clk $end
$var reg 1 & cs $end
$var reg 8 ' data_in1 [7:0] $end
$var reg 8 ( data_in2 [7:0] $end
$var reg 1 ) read1 $end
$var reg 1 * read2 $end
$var reg 1 + write1 $end
$var reg 1 , write2 $end
$var integer 32 - k [31:0] $end
$scope module DUT $end
$var wire 10 . addr1 [9:0] $end
$var wire 10 / addr2 [9:0] $end
$var wire 1 % clk $end
$var wire 1 & cs $end
$var wire 8 0 data_in1 [7:0] $end
$var wire 8 1 data_in2 [7:0] $end
$var wire 1 ) read1 $end
$var wire 1 * read2 $end
$var wire 1 + write1 $end
$var wire 1 , write2 $end
$var reg 8 2 data_out1 [7:0] $end
$var reg 8 3 data_out2 [7:0] $end
$upscope $end
$upscope $end
$enddefinitions $end
$comment Show the parameter values. $end
$dumpall
$end
#0
$dumpvars
bx 3
bx 2
bx 1
bx 0
bx /
bx .
b0 -
x,
x+
x*
x)
bx (
bx '
1&
0%
bx $
bx #
bx "
bx !
$end
#5
1%
#10
0%
b1 -
#15
1%
#20
0%
b10 -
#25
1%
#30
0%
b11 -
#35
1%
#40
0%
b100 -
#45
1%
#50
0%
b101 -
#55
1%
#60
0%
b110 -
#65
1%
#70
0%
b111 -
#75
1%
#80
0%
b1000 -
#85
1%
#90
0%
b1001 -
#95
1%
#100
0%
b1010 -
#105
1%
#110
0%
b1011 -
#115
1%
#120
0%
b1100 -
#125
1%
#130
0%
b1101 -
#135
1%
#140
0%
b1110 -
#145
1%
#150
0%
b1111 -
#155
1%
#160
0%
b10000 -
#165
1%
#170
0%
b10001 -
#175
1%
#180
0%
b10010 -
#185
1%
#190
0%
b10011 -
#195
1%
#200
0%
b10100 -
#205
1%
#210
0%
b10101 -
#215
1%
#220
0%
b10110 -
#225
1%
#230
0%
b10111 -
#235
1%
#240
0%
b11000 -
#245
1%
#250
0%
b11001 -
#255
1%
#260
0%
b11010 -
#265
1%
#270
0%
b11011 -
#275
1%
#280
0%
b11100 -
#285
1%
#290
0%
b11101 -
#295
1%
#300
0%
b11110 -
#305
1%
#310
0%
b11111 -
#315
1%
#320
0%
b100000 -
#325
1%
#330
0%
b100001 -
#335
1%
#340
0%
b100010 -
#345
1%
#350
0%
b100011 -
#355
1%
#360
0%
b100100 -
#365
1%
#370
0%
b100101 -
#375
1%
#380
0%
b100110 -
#385
1%
#390
0%
b100111 -
#395
1%
#400
0%
b101000 -
#405
1%
#410
0%
b101001 -
#415
1%
#420
0%
b101010 -
#425
1%
#430
0%
b101011 -
#435
1%
#440
0%
b101100 -
#445
1%
#450
0%
b101101 -
#455
1%
#460
0%
b101110 -
#465
1%
#470
0%
b101111 -
#475
1%
#480
0%
b110000 -
#485
1%
#490
0%
b110001 -
#495
1%
#500
0%
b110010 -
#505
1%
#510
0%
b110011 -
#515
1%
#520
0%
b110100 -
#525
1%
#530
0%
b110101 -
#535
1%
#540
0%
b110110 -
#545
1%
#550
0%
b110111 -
#555
1%
#560
0%
b111000 -
#565
1%
#570
0%
b111001 -
#575
1%
#580
0%
b111010 -
#585
1%
#590
0%
b111011 -
#595
1%
#600
0%
b111100 -
#605
1%
#610
0%
b111101 -
#615
1%
#620
0%
b111110 -
#625
1%
#630
0%
b111111 -
#635
1%
#640
0%
b1000000 -
#645
1%
#650
0%
b1000001 -
#655
1%
#660
0%
b1000010 -
#665
1%
#670
0%
b1000011 -
#675
1%
#680
0%
b1000100 -
#685
1%
#690
0%
b1000101 -
#695
1%
#700
0%
b1000110 -
#705
1%
#710
0%
b1000111 -
#715
1%
#720
0%
b1001000 -
#725
1%
#730
0%
b1001001 -
#735
1%
#740
0%
b1001010 -
#745
1%
#750
0%
b1001011 -
#755
1%
#760
0%
b1001100 -
#765
1%
#770
0%
b1001101 -
#775
1%
#780
0%
b1001110 -
#785
1%
#790
0%
b1001111 -
#795
1%
#800
0%
b1010000 -
#805
1%
#810
0%
b1010001 -
#815
1%
#820
0%
b1010010 -
#825
1%
#830
0%
b1010011 -
#835
1%
#840
0%
b1010100 -
#845
1%
#850
0%
b1010101 -
#855
1%
#860
0%
b1010110 -
#865
1%
#870
0%
b1010111 -
#875
1%
#880
0%
b1011000 -
#885
1%
#890
0%
b1011001 -
#895
1%
#900
0%
b1011010 -
#905
1%
#910
0%
b1011011 -
#915
1%
#920
0%
b1011100 -
#925
1%
#930
0%
b1011101 -
#935
1%
#940
0%
b1011110 -
#945
1%
#950
0%
b1011111 -
#955
1%
#960
0%
b1100000 -
#965
1%
#970
0%
b1100001 -
#975
1%
#980
0%
b1100010 -
#985
1%
#990
0%
b1100011 -
#995
1%
#1000
0%
b1100100 -
#1005
1%
#1010
0%
b1 $
b1 /
1*
b0 #
b0 .
1)
#1015
b1010 !
b1010 3
b0 "
b0 2
1%
