Vending_machine/vending_machine_FSM.v
module vending_machine_FSM(
    input clk,
    input reset,
    input [3:0] coin,
    output reg  dispense
);
    reg [1:0] state,next_state;
    reg [3:0] collected_amt;

    localparam IDLE=2'b00,COLL_5=2'b01,COLL_10=2'b10,COLL_15=2'b11;

    always @(posedge clk or posedge reset) begin
        if(reset) begin
            state<=IDLE;
            dispense<=0;
            collected_amt<=4'h0;
        end
        else state<=next_state;
    end

    always @(*) begin
        case(state)
            IDLE:begin
                if(coin==4'h5) next_state=COLL_5;
                else if(coin==4'ha) next_state=COLL_10;
                else next_state=IDLE;
            end
            COLL_5:begin
                if(coin==4'h5) next_state=COLL_10;
                else if(coin==4'ha) next_state=COLL_15;
                else next_state=COLL_5;
            end
            COLL_10:begin
                if(coin==4'h5) next_state=COLL_15;
                else if(coin==4'ha) next_state=COLL_15;
                else next_state=COLL_10;
            end
            COLL_15:begin
                next_state=IDLE;
            end
        endcase
    end

    always @(*) begin
        case(state)
            IDLE:begin
                dispense<=0;
                collected_amt<=4'h0;
            end
            COLL_5:begin
                dispense<=0;
                collected_amt<=4'h5;
            end
            COLL_10:begin
                dispense<=0;
                collected_amt<=4'ha;
            end
            COLL_15:begin
                collected_amt<=4'hf;
            end
            default:begin
                dispense<=0;
                collected_amt<=4'h0;
            end
        endcase
        dispense = (state == COLL_15);
    end

endmodule

Vending_machine/tb_vending_machine.v
module tb_vending_machine;
    reg clk,reset;
    reg [3:0] coin;
    wire dispense;

    vending_machine_FSM DUT(clk,reset,coin,dispense);
    initial begin
        clk=0;
        reset=0;
        coin=4'h0;
    end
    always #5 clk=~clk;
    initial begin
        #15 reset=1;
        #10 reset=0;

        #10 coin=4'h5;
        #10 coin=4'h5;
        #10 coin=4'h5;

        #50 $finish;
    end
    initial begin
        $dumpfile("vending_machine.vcd");
        $dumpvars(0,tb_vending_machine);
    end

endmodule

Vending_machine/vending_machine.vcd
$date
	Fri Jul 24 18:22:57 2026
$end
$version
	Icarus Verilog
$end
$timescale
	1s
$end
$scope module tb_vending_machine $end
$var wire 1 ! dispense $end
$var reg 1 " clk $end
$var reg 4 # coin [3:0] $end
$var reg 1 $ reset $end
$scope module DUT $end
$var wire 1 " clk $end
$var wire 4 % coin [3:0] $end
$var wire 1 $ reset $end
$var parameter 2 & COLL_10 $end
$var parameter 2 ' COLL_15 $end
$var parameter 2 ( COLL_5 $end
$var parameter 2 ) IDLE $end
$var reg 4 * collected_amt [3:0] $end
$var reg 1 ! dispense $end
$var reg 2 + next_state [1:0] $end
$var reg 2 , state [1:0] $end
$upscope $end
$upscope $end
$enddefinitions $end
$comment Show the parameter values. $end
$dumpall
b0 )
b1 (
b11 '
b10 &
$end
#0
$dumpvars
bx ,
bx +
bx *
b0 %
0$
b0 #
0"
x!
$end
#5
1"
#10
0"
#15
b0 +
b0 *
0!
b0 ,
1"
1$
#20
0"
#25
1"
0$
#30
0"
#35
b101 *
0!
b1 ,
b10 +
1"
b101 #
b101 %
#40
0"
#45
b1010 *
0!
b11 +
b10 ,
1"
#50
0"
#55
b1111 *
1!
b0 +
b11 ,
1"
#60
0"
#65
b0 *
0!
b1 +
b0 ,
1"
#70
0"
#75
b101 *
0!
b10 +
b1 ,
1"
#80
0"
#85
b1010 *
0!
b11 +
b10 ,
1"
#90
0"
#95
b1111 *
1!
b0 +
b11 ,
1"
#100
0"
#105
b0 *
0!
b1 +
b0 ,
1"
