spi_protocol/Verilog Files/slave_controller.v
module slave_controller(
    input clk,          // Fast internal FPGA sys_clk
    input rst,
    input CPOL,
    input CPHA,
    
    // Asynchronous physical pins
    input CS_pin,       
    input SCLK_pin,     
    
    // Outputs to the Datapath
    output reg ld_data,
    output reg sft_data,
    output reg sample_data,
    
    // Outputs to the Top Module
    output reg Done,
    output safe_CS_out  // Sent to top module to control MISO Tri-State
);

    // --- 1. The 2-Flop Synchronizers ---
    reg [1:0] cs_sync;
    reg [1:0] sclk_sync;

    always @(posedge clk or posedge rst) begin
        if(rst) begin
            cs_sync   <= 2'b11; // Default CS is HIGH (idle)
            sclk_sync <= 2'b00; // Default SCLK assumes 0 (will adapt)
        end else begin
            cs_sync   <= {cs_sync[0], CS_pin};
            sclk_sync <= {sclk_sync[0], SCLK_pin};
        end
    end

    wire safe_CS   = cs_sync[1];
    wire safe_sclk = sclk_sync[1];
    assign safe_CS_out = safe_CS;

    // --- 2. The Edge Detectors ---
    reg prev_cs;
    reg prev_sclk;

    always @(posedge clk or posedge rst) begin
        if(rst) begin
            prev_cs   <= 1'b1;
            prev_sclk <= 1'b0;
        end else begin
            prev_cs   <= safe_CS;
            prev_sclk <= safe_sclk;
        end
    end

    // 1-tick pulses for the FSM to watch
    wire cs_falling_edge = prev_cs & ~safe_CS;
    wire sclk_rising     = ~prev_sclk & safe_sclk;
    wire sclk_falling    = prev_sclk & ~safe_sclk;

    // --- 3. The Boolean Edge Router (CPOL/CPHA) ---
    wire rule_A = (CPOL == CPHA);
    wire do_sample = rule_A ? sclk_rising : sclk_falling;
    wire do_shift  = rule_A ? sclk_falling : sclk_rising;

    // --- 4. The FSM ---
    localparam IDLE     = 2'b00,
               START    = 2'b01,
               TRANSFER = 2'b10,
               DONE     = 2'b11;
               
    reg [1:0] state, next_state;
    reg [3:0] bit_counter;

    always @(posedge clk or posedge rst) begin
        if(rst) begin
            state <= IDLE;
            bit_counter <= 0;
            ld_data <= 0;
            sft_data <= 0;
            sample_data <= 0;
            Done <= 0;
        end 
        else if (safe_CS == 1'b1) begin
            // Asynchronous reset for the transaction if CS goes high
            state <= IDLE;
            bit_counter <= 0;
            ld_data <= 0;
            sft_data <= 0;
            sample_data <= 0;
            Done <= 0;
        end 
        else begin
            state <= next_state;
            
            // Default datapath controls to 0 to create 1-tick pulses
            ld_data <= 0;
            sft_data <= 0;
            sample_data <= 0;
            Done <= 0;

            case(state)
                IDLE: begin
                    bit_counter <= 0;
                end
                
                START: begin
                    ld_data <= 1; // Pulse load to grab FPGA data
                end
                
                TRANSFER: begin
                    if (do_sample) begin
                        sample_data <= 1;
                        bit_counter <= bit_counter + 1;
                    end
                    if (do_shift) begin
                        sft_data <= 1;
                    end
                end
                
                DONE: begin
                    Done <= 1; // Pulse Done flag
                end
            endcase
        end
    end

    always @(*) begin
        next_state = state;
        case(state)
            IDLE:     if(cs_falling_edge) next_state = START;
            START:    next_state = TRANSFER;
            TRANSFER: if(bit_counter == 4'h8) next_state = DONE;
            DONE:     next_state = IDLE;
        endcase
    end

endmodule

spi_protocol/Verilog Files/datapath.v
module universal_datapath(
    input clk,
    input rst,
    input [7:0] tx_data_in,
    input serial_in,     
    input ld_data,
    input sft_data,
    input sample_data,
    output serial_out,   
    output reg [7:0] rx_data_out
);

    reg [7:0] tx_reg;
    reg [7:0] rx_reg;

    // Output the Most Significant Bit (MSB) first
    assign serial_out = tx_reg[7]; 

    always @(posedge clk or posedge rst) begin
        if(rst) begin
            tx_reg <= 8'h00;
            rx_reg <= 8'h00;
            rx_data_out <= 8'h00;
        end 
        else begin
            // Transmit Logic (Shift Out)
            if(ld_data) begin
                tx_reg <= tx_data_in;
            end 
            else if(sft_data) begin
                tx_reg <= {tx_reg[6:0], 1'b0};
            end

            // Receive Logic (Sample In)
            if(sample_data) begin
                rx_reg <= {rx_reg[6:0], serial_in};
                rx_data_out <= {rx_reg[6:0], serial_in}; // Expose to main system
            end
        end
    end
endmodule

spi_protocol/Verilog Files/spi_slave_top_module.v
module spi_slave_top(
    input clk,            // sys_clk
    input rst,
    
    // SPI Configuration
    input CPOL,
    input CPHA,
    
    // FPGA System Interface
    input [7:0] tx_data,  // Data you want the slave to send to master
    output [7:0] rx_data, // Data the slave received from master
    output rx_done,       // Pulses high when rx_data is valid
    
    // Physical SPI Pins
    input CS,
    input SCLK,
    input MOSI,
    output MISO           // Note: Must be type 'wire' for Tri-State
);

    // --- Internal Wires ---
    wire internal_ld, internal_sft, internal_smp;
    wire safe_CS_internal;
    wire serial_out_wire;

    // --- MOSI Synchronizer ---
    // MOSI must also be synchronized to avoid metastability in the datapath
    reg [1:0] mosi_sync;
    always @(posedge clk or posedge rst) begin
        if(rst) mosi_sync <= 2'b00;
        else    mosi_sync <= {mosi_sync[0], MOSI};
    end
    wire safe_MOSI = mosi_sync[1];

    // --- Tri-State MISO Buffer ---
    // If CS is low (active), drive the wire. If high, disconnect (High-Z).
    assign MISO = (safe_CS_internal == 1'b0) ? serial_out_wire : 1'bz;

    // --- Instantiations ---
    universal_datapath Datapath_Inst (
        .clk(clk),
        .rst(rst),
        .tx_data_in(tx_data),
        .serial_in(safe_MOSI),      // Safe MOSI feeds the shift register
        .ld_data(internal_ld),
        .sft_data(internal_sft),
        .sample_data(internal_smp),
        .serial_out(serial_out_wire),// Feeds the Tri-State buffer
        .rx_data_out(rx_data)
    );

    slave_controller Controller_Inst(
        .clk(clk),
        .rst(rst),
        .CPOL(CPOL),
        .CPHA(CPHA),
        .CS_pin(CS),
        .SCLK_pin(SCLK),
        .ld_data(internal_ld),
        .sft_data(internal_sft),
        .sample_data(internal_smp),
        .Done(rx_done),
        .safe_CS_out(safe_CS_internal) // Feeds the Tri-State buffer
    );

endmodule

spi_protocol/Verilog_files/master_controller.v
module master_controller(
    input  wire clk,
    input  wire rst,
    input  wire start,
    input  wire CPOL,
    input  wire CPHA,

    // Datapath Control Pulses
    output reg  load_en,
    output reg  shift_en,
    output reg  sample_en,
    
    // External SPI & System Signals
    output reg  cs_n,       // _n indicates Active-Low
    output reg  done_flag,
    output wire sclk_out
);

    // --- FSM State Definitions ---
    localparam IDLE     = 2'b00,
            START    = 2'b01,
            TRANSFER = 2'b10,
            DONE     = 2'b11;
            
    reg [1:0] state, next_state;

    // --- 1. The Metronome (Baud Rate Generator) ---
    reg [3:0] baud_counter;
    reg sclk_tick; // Replaces 'toggle' to be more descriptive

    always @(posedge clk or posedge rst) begin
        if(rst) begin
            baud_counter <= 0;
            sclk_tick    <= 0;
        end
        else if (state == IDLE || state == DONE) begin 
            baud_counter <= 0;
            sclk_tick    <= 0;
        end
        else begin
            if(baud_counter == 4'h5) begin // Adjust for desired SPI speed
                baud_counter <= 0;
                sclk_tick    <= 1; // 1-tick pulse
            end
            else begin
                baud_counter <= baud_counter + 1;
                sclk_tick    <= 0;
            end
        end
    end
    
    // --- 2. 16-Edge Tracker ---
    reg [3:0] edge_count;
    wire even_edge = ~edge_count[0];
    wire odd_edge  =  edge_count[0];

    always @(posedge clk or posedge rst) begin
        if(rst) begin
            edge_count <= 0;
        end
        else if (state == IDLE || state == DONE) begin
            edge_count <= 0; 
        end
        else if (sclk_tick) begin // Only count when metronome ticks
            if(edge_count == 4'hF) 
                edge_count <= 0;
            else 
                edge_count <= edge_count + 1;
        end
    end

    // --- 3. SCLK Generator (Fixed Multiple Driver Bug) ---
    reg internal_sclk;
    assign sclk_out = internal_sclk;
    
    always @(posedge clk or posedge rst) begin
        if(rst) begin
            internal_sclk <= CPOL;
        end
        else if (state == IDLE || state == DONE) begin
            internal_sclk <= CPOL; // Safely forces SCLK to idle state here
        end
        else if (state == TRANSFER && sclk_tick) begin
            internal_sclk <= ~internal_sclk; // Flip SCLK on every tick
        end
    end

    // --- 4. FSM Sequential Logic ---
    always @(posedge clk or posedge rst) begin
        if(rst) begin
            state       <= IDLE;
            cs_n        <= 1;
            load_en     <= 0;
            shift_en    <= 0;
            sample_en   <= 0;
            done_flag   <= 0;
        end
        else begin
            state <= next_state;
            
            // Default outputs to 0
            load_en   <= 0;
            shift_en  <= 0;
            sample_en <= 0;
            done_flag <= 0;
            
            case(state) 
                IDLE: begin
                    cs_n <= 1; // Sleep
                end
                
                START: begin
                    cs_n    <= 0; // Wake up slave
                    load_en <= 1; // Load data into datapath
                end
                
                TRANSFER: begin
                    cs_n <= 0; // Keep chip select active
                    
                    if(sclk_tick) begin
                        if(CPHA == 0) begin
                            if(even_edge) sample_en <= 1;
                            if(odd_edge)  shift_en  <= 1;
                        end
                        else if(CPHA == 1) begin
                            if(even_edge) shift_en  <= 1;
                            if(odd_edge)  sample_en <= 1;
                        end
                    end
                end
                
                DONE: begin
                    cs_n      <= 1; // Deselect slave
                    done_flag <= 1; // Alert main system
                end
            endcase
        end
    end

    // --- 5. FSM Next-State Logic ---
    always @(*) begin
        next_state = state; 
        
        case(state) 
            IDLE: begin
                if(start) next_state = START;
            end
            START: begin
                next_state = TRANSFER;
            end
            TRANSFER: begin
                // Wait for the 15th edge AND the final metronome tick to complete it
                if(edge_count == 4'hF && sclk_tick) begin
                    next_state = DONE;
                end
            end
            DONE: begin
                next_state = IDLE;
            end
        endcase
    end
endmodule

spi_protocol/Verilog_files/spi_master_top_module.v
module spi_master_top_module(
    input  wire clk,
    input  wire rst,
    input  wire start,
    input  wire [7:0] data_in,
    input  wire CPOL,
    input  wire CPHA,
    input  wire miso,           // FIXED: Added the missing MISO input pin!

    output wire cs_n,           // Updated name: Active-low Chip Select
    output wire done_flag,      // Updated name
    output wire sclk,
    output wire mosi,
    output wire [7:0] data_out
);

    // Internal wires connecting the Controller (Brain) to the Datapath (Muscle)
    wire load_en;
    wire shift_en;
    wire sample_en;

    // --- Instantiation of the Universal Datapath ---
    // Notice how we map the generic "serial" ports to the Master's specific pins
    universal_datapath Datapath_Inst (
        .clk(clk),
        .rst(rst),
        .tx_data_in(data_in),   // Direct connection, no 'Bus' wire needed
        .serial_in(miso),       // For a Master, serial_in is connected to MISO
        .ld_data(load_en),      
        .sft_data(shift_en),
        .sample_data(sample_en),
        .serial_out(mosi),      // For a Master, serial_out is connected to MOSI
        .rx_data_out(data_out)
    );

    // --- Instantiation of the Master Controller ---
    master_controller Controller_Inst (
        .clk(clk),
        .rst(rst),
        .start(start),
        .CPOL(CPOL),
        .CPHA(CPHA),
        .load_en(load_en),
        .shift_en(shift_en),
        .sample_en(sample_en),
        .cs_n(cs_n),            
        .done_flag(done_flag),
        .sclk_out(sclk)         
    );

endmodule

spi_protocol/Verilog Files/spi_top_module.v
module top_spi_module(
    //common inputs
    input clk,
    input rst,
    input CPOL,
    input CPHA,

    //master-side inputs
    input [7:0] master_data_in,
    input start,
    //master outputs
    output cs_line,
    output sclk_line,
    output mosi_line,
    output master_tx_done,
    output [7:0] master_data_out,

    //slave side inputs
    input [7:0] slave_data_in,
    //slave outputs
    output [7:0] slave_data_out,
    output slave_rx_done,
    output miso_line
);

    spi_master_top_module spi_master(
        .clk(clk),
        .rst(rst),
        .CPOL(CPOL),
        .CPHA(CPHA),
        .start(start),
        .data_in(master_data_in),
        .miso(miso_line),
        .cs_n(cs_line),
        .done_flag(master_tx_done),
        .sclk(sclk_line),
        .mosi(mosi_line),
        .data_out(master_data_out)
    );

    spi_slave_top spi_slave(
        .clk(clk),
        .rst(rst),
        .CPOL(CPOL),
        .CPHA(CPHA),
        .tx_data(slave_data_in),
        .rx_data(slave_data_out),
        .rx_done(slave_rx_done),
        .CS(cs_line),
        .SCLK(sclk_line),
        .MOSI(mosi_line),
        .MISO(miso_line)
    );

endmodule

spi_protocol/Testbenche files/tb_spi_top_module.v
module tb_spi_top_module;
    reg clk,rst,CPOL,CPHA;
    reg [7:0] master_data_in,slave_data_in;
    reg start;

    wire cs_line,sclk_line,mosi_line,master_tx_done,slave_rx_done,miso_line;
    wire [7:0] slave_data_out;

    top_spi_module DUT(
        .clk(clk),
        .rst(rst),
        .CPOL(CPOL),
        .CPHA(CPHA),
        .master_data_in(master_data_in),
        .slave_data_in(slave_data_in),
        .start(start),
        .cs_line(cs_line),
        .sclk_line(sclk_line),
        .mosi_line(mosi_line),
        .master_tx_done(master_tx_done),
        .slave_rx_done(slave_rx_done),
        .miso_line(miso_line),
        .slave_data_out(slave_data_out)
    );

    initial begin
        clk=0;
        rst=0;
        CPOL=0;
        CPHA=0;
        master_data_in=8'h0a;
        slave_data_in=8'h0b;
    end
    always #5 clk=~clk;
    initial begin
        #15 rst=1;
        #10 rst=0;
        #10;
        start=1;
        #10 start=0;

        #1200;
        $finish;
    end
    initial begin
        $dumpfile("spi_top_module.vcd");
        $dumpvars(0,tb_spi_top_module);
    end

endmodule

spi_protocol/Verilog Files/spi_top_module.vcd
$date
	Thu Aug 20 15:23:57 2026
$end
$version
	Icarus Verilog
$end
$timescale
	1s
$end
$scope module tb_spi_top_module $end
$var wire 1 ! slave_rx_done $end
$var wire 8 " slave_data_out [7:0] $end
$var wire 1 # sclk_line $end
$var wire 1 $ mosi_line $end
$var wire 1 % miso_line $end
$var wire 1 & master_tx_done $end
$var wire 1 ' cs_line $end
$var reg 1 ( CPHA $end
$var reg 1 ) CPOL $end
$var reg 1 * clk $end
$var reg 8 + master_data_in [7:0] $end
$var reg 1 , rst $end
$var reg 8 - slave_data_in [7:0] $end
$var reg 1 . start $end
$scope module DUT $end
$var wire 1 ( CPHA $end
$var wire 1 ) CPOL $end
$var wire 1 * clk $end
$var wire 8 / master_data_in [7:0] $end
$var wire 1 , rst $end
$var wire 8 0 slave_data_in [7:0] $end
$var wire 1 . start $end
$var wire 1 ! slave_rx_done $end
$var wire 8 1 slave_data_out [7:0] $end
$var wire 1 # sclk_line $end
$var wire 1 $ mosi_line $end
$var wire 1 % miso_line $end
$var wire 1 & master_tx_done $end
$var wire 8 2 master_data_out [7:0] $end
$var wire 1 ' cs_line $end
$scope module spi_master $end
$var wire 1 ( CPHA $end
$var wire 1 ) CPOL $end
$var wire 1 * clk $end
$var wire 8 3 data_in [7:0] $end
$var wire 1 , rst $end
$var wire 1 . start $end
$var wire 1 4 shift_en $end
$var wire 1 # sclk $end
$var wire 1 5 sample_en $end
$var wire 1 $ mosi $end
$var wire 1 % miso $end
$var wire 1 6 load_en $end
$var wire 1 & done_flag $end
$var wire 8 7 data_out [7:0] $end
$var wire 1 ' cs_n $end
$scope module Controller_Inst $end
$var wire 1 ( CPHA $end
$var wire 1 ) CPOL $end
$var wire 1 * clk $end
$var wire 1 8 even_edge $end
$var wire 1 , rst $end
$var wire 1 # sclk_out $end
$var wire 1 . start $end
$var wire 1 9 odd_edge $end
$var parameter 2 : DONE $end
$var parameter 2 ; IDLE $end
$var parameter 2 < START $end
$var parameter 2 = TRANSFER $end
$var reg 4 > baud_counter [3:0] $end
$var reg 1 ' cs_n $end
$var reg 1 & done_flag $end
$var reg 4 ? edge_count [3:0] $end
$var reg 1 @ internal_sclk $end
$var reg 1 6 load_en $end
$var reg 2 A next_state [1:0] $end
$var reg 1 5 sample_en $end
$var reg 1 B sclk_tick $end
$var reg 1 4 shift_en $end
$var reg 2 C state [1:0] $end
$upscope $end
$scope module Datapath_Inst $end
$var wire 1 * clk $end
$var wire 1 6 ld_data $end
$var wire 1 , rst $end
$var wire 1 5 sample_data $end
$var wire 1 4 sft_data $end
$var wire 8 D tx_data_in [7:0] $end
$var wire 1 $ serial_out $end
$var wire 1 % serial_in $end
$var reg 8 E rx_data_out [7:0] $end
$var reg 8 F rx_reg [7:0] $end
$var reg 8 G tx_reg [7:0] $end
$upscope $end
$upscope $end
$scope module spi_slave $end
$var wire 1 ( CPHA $end
$var wire 1 ) CPOL $end
$var wire 1 ' CS $end
$var wire 1 $ MOSI $end
$var wire 1 # SCLK $end
$var wire 1 * clk $end
$var wire 1 , rst $end
$var wire 8 H tx_data [7:0] $end
$var wire 1 I serial_out_wire $end
$var wire 1 J safe_MOSI $end
$var wire 1 K safe_CS_internal $end
$var wire 1 ! rx_done $end
$var wire 8 L rx_data [7:0] $end
$var wire 1 M internal_smp $end
$var wire 1 N internal_sft $end
$var wire 1 O internal_ld $end
$var wire 1 % MISO $end
$var reg 2 P mosi_sync [1:0] $end
$scope module Controller_Inst $end
$var wire 1 ( CPHA $end
$var wire 1 ) CPOL $end
$var wire 1 ' CS_pin $end
$var wire 1 # SCLK_pin $end
$var wire 1 * clk $end
$var wire 1 Q cs_falling_edge $end
$var wire 1 , rst $end
$var wire 1 R rule_A $end
$var wire 1 K safe_CS_out $end
$var wire 1 S sclk_falling $end
$var wire 1 T sclk_rising $end
$var wire 1 U safe_sclk $end
$var wire 1 V safe_CS $end
$var wire 1 W do_shift $end
$var wire 1 X do_sample $end
$var parameter 2 Y DONE $end
$var parameter 2 Z IDLE $end
$var parameter 2 [ START $end
$var parameter 2 \ TRANSFER $end
$var reg 1 ! Done $end
$var reg 4 ] bit_counter [3:0] $end
$var reg 2 ^ cs_sync [1:0] $end
$var reg 1 O ld_data $end
$var reg 2 _ next_state [1:0] $end
$var reg 1 ` prev_cs $end
$var reg 1 a prev_sclk $end
$var reg 1 M sample_data $end
$var reg 2 b sclk_sync [1:0] $end
$var reg 1 N sft_data $end
$var reg 2 c state [1:0] $end
$upscope $end
$scope module Datapath_Inst $end
$var wire 1 * clk $end
$var wire 1 O ld_data $end
$var wire 1 , rst $end
$var wire 1 M sample_data $end
$var wire 1 J serial_in $end
$var wire 1 N sft_data $end
$var wire 8 d tx_data_in [7:0] $end
$var wire 1 I serial_out $end
$var reg 8 e rx_data_out [7:0] $end
$var reg 8 f rx_reg [7:0] $end
$var reg 8 g tx_reg [7:0] $end
$upscope $end
$upscope $end
$upscope $end
$upscope $end
$enddefinitions $end
$comment Show the parameter values. $end
$dumpall
b10 \
b1 [
b0 Z
b11 Y
b10 =
b1 <
b0 ;
b11 :
$end
#0
$dumpvars
bx g
bx f
bx e
b1011 d
bx c
bx b
xa
x`
bx _
bx ^
bx ]
xX
xW
xV
xU
xT
xS
1R
xQ
bx P
xO
xN
xM
bx L
xK
xJ
xI
b1011 H
bx G
bx F
bx E
b1010 D
bx C
xB
bx A
x@
bx ?
bx >
x9
x8
bx 7
x6
x5
x4
b1010 3
bx 2
bx 1
b1011 0
b1010 /
x.
b1011 -
0,
b1010 +
0*
0)
0(
x'
x&
x%
x$
x#
bx "
x!
$end
#5
0B
0&
05
04
06
0!
0M
0N
0O
1*
#10
0*
#15
0X
0Q
z%
0W
0T
18
0J
b0 _
0S
0U
1K
1V
0I
b0 A
09
0$
b0 P
b0 ]
b0 c
0a
1`
b0 b
b11 ^
b0 "
b0 1
b0 L
b0 e
b0 f
b0 g
1'
b0 C
0#
0@
b0 ?
b0 >
b0 2
b0 7
b0 E
b0 F
b0 G
1*
1,
#20
0*
#25
1*
0,
#30
0*
#35
b1 C
b10 A
1*
1.
#40
0*
#45
b1 >
16
0'
b10 C
b10 A
1*
0.
#50
0*
#55
b10 ^
06
b10 >
b1010 G
1*
#60
0*
#65
b1 _
1Q
0%
0K
0V
b11 >
b0 ^
1*
#70
0*
#75
b10 _
0Q
b1 c
0`
b100 >
1*
#80
0*
#85
b101 >
1O
b10 c
1*
#90
0*
#95
0O
b1011 g
1B
b0 >
1*
#100
0*
#105
08
19
0B
b1 >
b1 ?
1#
1@
15
1*
#110
0*
#115
b1 b
05
b10 >
1*
#120
0*
#125
1X
1T
1U
b11 >
b11 b
1*
#130
0*
#135
0X
0T
b1 ]
1M
1a
b100 >
1*
#140
0*
#145
b101 >
0M
1*
#150
0*
#155
1B
b0 >
1*
#160
0*
#165
18
09
0B
b1 >
b10 ?
0#
0@
14
1*
#170
0*
#175
b10 b
04
b10 >
b10100 G
1*
#180
0*
#185
1W
1S
0U
b11 >
b0 b
1*
#190
0*
#195
0W
0S
1N
0a
b100 >
1*
#200
0*
#205
b101 >
b10110 g
0N
1*
#210
0*
#215
1B
b0 >
1*
#220
0*
#225
08
19
0B
b1 >
b11 ?
1#
1@
15
1*
#230
0*
#235
b1 b
05
b10 >
1*
#240
0*
#245
1X
1T
1U
b11 >
b11 b
1*
#250
0*
#255
0X
0T
b10 ]
1M
1a
b100 >
1*
#260
0*
#265
b101 >
0M
1*
#270
0*
#275
1B
b0 >
1*
#280
0*
#285
18
09
0B
b1 >
b100 ?
0#
0@
14
1*
#290
0*
#295
b10 b
04
b10 >
b101000 G
1*
#300
0*
#305
1W
1S
0U
b11 >
b0 b
1*
#310
0*
#315
0W
0S
1N
0a
b100 >
1*
#320
0*
#325
b101 >
b101100 g
0N
1*
#330
0*
#335
1B
b0 >
1*
#340
0*
#345
08
19
0B
b1 >
b101 ?
1#
1@
15
1*
#350
0*
#355
b1 b
05
b10 >
1*
#360
0*
#365
1X
1T
1U
b11 >
b11 b
1*
#370
0*
#375
0X
0T
b11 ]
1M
1a
b100 >
1*
#380
0*
#385
b101 >
0M
1*
#390
0*
#395
1B
b0 >
1*
#400
0*
#405
18
09
0B
b1 >
b110 ?
0#
0@
14
1*
#410
0*
#415
b10 b
04
b10 >
b1010000 G
1*
#420
0*
#425
1W
1S
0U
b11 >
b0 b
1*
#430
0*
#435
0W
0S
1N
0a
b100 >
1*
#440
0*
#445
b101 >
b1011000 g
0N
1*
#450
0*
#455
1B
b0 >
1*
#460
0*
#465
08
19
0B
b1 >
b111 ?
1#
1@
15
1*
#470
0*
#475
b1 b
05
b10 >
1*
#480
0*
#485
1X
1T
1U
b11 >
b11 b
1*
#490
0*
#495
0X
0T
b100 ]
1M
1a
b100 >
1*
#500
0*
#505
b101 >
0M
1*
#510
0*
#515
1B
b0 >
1*
#520
0*
#525
18
09
0B
b1 >
b1000 ?
0#
0@
14
1*
#530
0*
#535
1$
b10 b
04
b10 >
b10100000 G
1*
#540
0*
#545
1W
1S
0U
b11 >
b0 b
b1 P
1*
#550
0*
#555
0W
1J
0S
b11 P
1N
0a
b100 >
1*
#560
0*
#565
1%
1I
b101 >
b10110000 g
0N
1*
#570
0*
#575
1B
b0 >
1*
#580
0*
#585
08
19
0B
b1 >
b1001 ?
1#
1@
15
1*
#590
0*
#595
b1 b
05
b10 >
b1 2
b1 7
b1 E
b1 F
1*
#600
0*
#605
1X
1T
1U
b11 >
b11 b
1*
#610
0*
#615
0X
0T
b101 ]
1M
1a
b100 >
1*
#620
0*
#625
b101 >
b1 "
b1 1
b1 L
b1 e
b1 f
0M
1*
#630
0*
#635
1B
b0 >
1*
#640
0*
#645
18
09
0B
b1 >
b1010 ?
0#
0@
14
1*
#650
0*
#655
0$
b10 b
04
b10 >
b1000000 G
1*
#660
0*
#665
1W
1S
0U
b11 >
b0 b
b10 P
1*
#670
0*
#675
0W
0J
0S
b0 P
1N
0a
b100 >
1*
#680
0*
#685
0%
0I
b101 >
b1100000 g
0N
1*
#690
0*
#695
1B
b0 >
1*
#700
0*
#705
08
19
0B
b1 >
b1011 ?
1#
1@
15
1*
#710
0*
#715
b1 b
05
b10 >
b10 2
b10 7
b10 E
b10 F
1*
#720
0*
#725
1X
1T
1U
b11 >
b11 b
1*
#730
0*
#735
0X
0T
b110 ]
1M
1a
b100 >
1*
#740
0*
#745
b101 >
b10 "
b10 1
b10 L
b10 e
b10 f
0M
1*
#750
0*
#755
1B
b0 >
1*
#760
0*
#765
18
09
0B
b1 >
b1100 ?
0#
0@
14
1*
#770
0*
#775
1$
b10 b
04
b10 >
b10000000 G
1*
#780
0*
#785
1W
1S
0U
b11 >
b0 b
b1 P
1*
#790
0*
#795
0W
1J
0S
b11 P
1N
0a
b100 >
1*
#800
0*
#805
1%
1I
b101 >
b11000000 g
0N
1*
#810
0*
#815
1B
b0 >
1*
#820
0*
#825
08
19
0B
b1 >
b1101 ?
1#
1@
15
1*
#830
0*
#835
b1 b
05
b10 >
b101 2
b101 7
b101 E
b101 F
1*
#840
0*
#845
1X
1T
1U
b11 >
b11 b
1*
#850
0*
#855
0X
0T
b111 ]
1M
1a
b100 >
1*
#860
0*
#865
b101 >
b101 "
b101 1
b101 L
b101 e
b101 f
0M
1*
#870
0*
#875
1B
b0 >
1*
#880
0*
#885
18
09
0B
b1 >
b1110 ?
0#
0@
14
1*
#890
0*
#895
0$
b10 b
04
b10 >
b0 G
1*
#900
0*
#905
1W
1S
0U
b11 >
b0 b
b10 P
1*
#910
0*
#915
0W
0J
0S
b0 P
1N
0a
b100 >
1*
#920
0*
#925
b101 >
b10000000 g
0N
1*
#930
0*
#935
1B
b0 >
1*
#940
0*
#945
08
19
0B
b1 >
b1111 ?
1#
1@
15
1*
#950
0*
#955
b1 b
05
b10 >
b1011 2
b1011 7
b1011 E
b1011 F
1*
#960
0*
#965
1X
1T
1U
b11 >
b11 b
1*
#970
0*
#975
0X
0T
b11 _
b1000 ]
1M
1a
b100 >
1*
#980
0*
#985
b0 _
b101 >
b1010 "
b1010 1
b1010 L
b1010 e
b1010 f
0M
b11 c
1*
#990
0*
#995
b11 A
1!
b0 c
1B
b0 >
1*
#1000
0*
#1005
18
09
b0 A
0B
b1 >
b0 ?
0#
0@
14
b11 C
b0 ]
0!
1*
#1010
0*
#1015
b10 b
1&
1'
04
b0 C
b0 >
1*
#1020
0*
#1025
1W
1S
0U
0&
b0 b
b1 ^
1*
#1030
0*
#1035
z%
0W
0S
1K
1V
0a
b11 ^
1*
#1040
0*
#1045
1`
1*
