sequence_detector/Sequence_detector_FSM.v
module seq_detector(
    input clk,
    input reset,
    input input_bit,
    output reg detected,
    output reg [1:0] CurrState
);
    reg [1:0] state,next_state;
    localparam S0=2'b00,S1=2'b01,S2=2'b10,S3=2'b11;

    always @(posedge clk or posedge reset) begin
        if(reset) begin
            state<=S0;
            detected<=0;
        end 
        else state<=next_state;
    end

    always @(*) begin
        case(state)
            S0:begin
                if(input_bit) next_state=S1;
                else next_state=S0;
            end
            S1:begin
                if(input_bit) next_state=S1;
                else next_state=S2;
            end
            S2:begin
                if(input_bit) next_state=S3;
                else next_state=S0;
            end
            S3:begin
                if(input_bit) next_state=S1;
                else next_state=S2;
            end
            default:next_state=S0;
        endcase
    end

    always @(*) begin
        if(state==S3 && input_bit==1'b1) detected=1;
        else detected=0;
        CurrState=state;
    end

endmodule

sequence_detector/tb_sequence_detector.v
module tb_sequence_detector;
    reg clk;
    reg reset;
    reg input_bit;
    wire detected;
    wire [1:0] curr_state;

    seq_detector DUT(clk,reset,input_bit,detected,curr_state);
    initial begin
        clk=0;
        reset=0;
    end
    always #5 clk=~clk;
    initial begin
        #15 reset=1;
        #10 reset=0;
        #10 input_bit=1;
        #10 input_bit=1;
        #10 input_bit=0;
        #10 input_bit=1;
        #10 input_bit=1;
        #10 input_bit=0;
        #10 input_bit=1;
        #10 input_bit=1;
        #10 input_bit=0;
        #10 input_bit=1;
        #10 input_bit=1;
        #10 input_bit=1;

        #10 $finish;
    end
    initial begin
        $dumpfile("seq_detector.vcd");
        $dumpvars(0,tb_sequence_detector);
    end
endmodule

sequence_detector/seq_detector.vcd
$date
	Fri Jul 24 17:53:29 2026
$end
$version
	Icarus Verilog
$end
$timescale
	1s
$end
$scope module tb_sequence_detector $end
$var wire 1 ! detected $end
$var wire 2 " curr_state [1:0] $end
$var reg 1 # clk $end
$var reg 1 $ input_bit $end
$var reg 1 % reset $end
$scope module DUT $end
$var wire 1 # clk $end
$var wire 1 $ input_bit $end
$var wire 1 % reset $end
$var parameter 2 & S0 $end
$var parameter 2 ' S1 $end
$var parameter 2 ( S2 $end
$var parameter 2 ) S3 $end
$var reg 2 * CurrState [1:0] $end
$var reg 1 ! detected $end
$var reg 2 + next_state [1:0] $end
$var reg 2 , state [1:0] $end
$upscope $end
$upscope $end
$enddefinitions $end
$comment Show the parameter values. $end
$dumpall
b11 )
b10 (
b1 '
b0 &
$end
#0
$dumpvars
bx ,
bx +
bx *
0%
x$
0#
bx "
x!
$end
#5
1#
#10
0#
#15
b0 "
b0 *
b0 +
0!
b0 ,
1#
1%
#20
0#
#25
1#
0%
#30
0#
#35
b1 "
b1 *
b1 ,
b1 +
1#
1$
#40
0#
#45
1#
#50
0#
#55
b10 "
b10 *
b10 ,
b0 +
1#
0$
#60
0#
#65
b11 "
b11 *
1!
b11 ,
b1 +
1#
1$
#70
0#
#75
b1 "
b1 *
0!
b1 ,
1#
#80
0#
#85
b10 "
b10 *
b10 ,
b0 +
1#
0$
#90
0#
#95
b11 "
b11 *
1!
b11 ,
b1 +
1#
1$
#100
0#
#105
b1 "
b1 *
0!
b1 ,
1#
#110
0#
#115
b10 "
b10 *
b10 ,
b0 +
1#
0$
#120
0#
#125
b11 "
b11 *
1!
b11 ,
b1 +
1#
1$
#130
0#
#135
b1 "
b1 *
0!
b1 ,
1#
